netlist_carpentry/__init__.py
netlist_carpentry/py.typed
netlist_carpentry/core/__init__.py
netlist_carpentry/core/circuit.py
netlist_carpentry/core/exceptions.py
netlist_carpentry/core/enums/__init__.py
netlist_carpentry/core/enums/direction.py
netlist_carpentry/core/enums/element_type.py
netlist_carpentry/core/enums/signal.py
netlist_carpentry/core/graph/__init__.py
netlist_carpentry/core/graph/constraint.py
netlist_carpentry/core/graph/match.py
netlist_carpentry/core/graph/module_graph.py
netlist_carpentry/core/graph/pattern.py
netlist_carpentry/core/graph/pattern_generator.py
netlist_carpentry/core/graph/visualization/__init__.py
netlist_carpentry/core/graph/visualization/cytoscape.py
netlist_carpentry/core/graph/visualization/formatting.py
netlist_carpentry/core/graph/visualization/formatting_types.py
netlist_carpentry/core/graph/visualization/plotting.py
netlist_carpentry/core/graph/visualization/visualization_base.py
netlist_carpentry/core/netlist_elements/__init__.py
netlist_carpentry/core/netlist_elements/element_path.py
netlist_carpentry/core/netlist_elements/instance.py
netlist_carpentry/core/netlist_elements/module.py
netlist_carpentry/core/netlist_elements/netlist_element.py
netlist_carpentry/core/netlist_elements/port.py
netlist_carpentry/core/netlist_elements/port_segment.py
netlist_carpentry/core/netlist_elements/segment_base.py
netlist_carpentry/core/netlist_elements/wire.py
netlist_carpentry/core/netlist_elements/wire_segment.py
netlist_carpentry/core/netlist_elements/mixins/__init__.py
netlist_carpentry/core/netlist_elements/mixins/evaluation.py
netlist_carpentry/core/netlist_elements/mixins/graph_building.py
netlist_carpentry/core/netlist_elements/mixins/hooks.py
netlist_carpentry/core/netlist_elements/mixins/metadata.py
netlist_carpentry/core/netlist_elements/mixins/module_base.py
netlist_carpentry/core/netlist_elements/mixins/module_bfs.py
netlist_carpentry/core/netlist_elements/mixins/module_dfs.py
netlist_carpentry/core/protocols/__init__.py
netlist_carpentry-0.3.1.dist-info/METADATA
netlist_carpentry-0.3.1.dist-info/WHEEL
netlist_carpentry-0.3.1.dist-info/licenses/LICENSE
netlist_carpentry-0.3.1.dist-info/RECORD
