Metadata-Version: 2.4
Name: netlist-carpentry
Version: 0.3.1
Summary: A library for netlist modification and analysis
Project-URL: Homepage, https://github.com/IMMS-Ilmenau/netlist-carpentry
Project-URL: Documentation, https://IMMS-Ilmenau.github.io/netlist-carpentry
Author: Manuel Jirsak
Maintainer-email: Georg Gläser <georg.glaeser@imms.de>
License-File: LICENSE
Requires-Python: >=3.9
Requires-Dist: click>=8.1.8
Requires-Dist: dash-cytoscape>=1.0.2
Requires-Dist: ipykernel>=6.29.5
Requires-Dist: matplotlib>=3.9.4
Requires-Dist: mkdocs-jupyter>=0.25.1
Requires-Dist: networkx>=3.2.1
Requires-Dist: pydantic-ai>=0.8.1
Requires-Dist: pydantic>=2.10.6
Requires-Dist: pywellen>=0.19.3
Requires-Dist: rich>=13.9.4
Requires-Dist: scipy>=1.13.1
Requires-Dist: tqdm>=4.67.1
Requires-Dist: types-tqdm>=4.67.0.20250516
Requires-Dist: z3-solver>=4.15.0.0
Provides-Extra: type-stubs
Requires-Dist: pytest-stub; extra == 'type-stubs'
Requires-Dist: types-networkx; extra == 'type-stubs'
